mycalc/excalculator.py
calforossHW-0.0.1.dist-info/LICENSE
calforossHW-0.0.1.dist-info/METADATA
calforossHW-0.0.1.dist-info/WHEEL
calforossHW-0.0.1.dist-info/top_level.txt
calforossHW-0.0.1.dist-info/RECORD
