Metadata-Version: 2.1
Name: calforossHW
Version: 0.0.1
Summary: Calculator of Oss Class Homework
Home-page: 
Author: kanghyeon
Classifier: Programming Language :: Python :: 3
License-File: LICENSE
